{"stats":{"minecraft:mined":{"minecraft:dead_bush":10,"minecraft:sand":10},"minecraft:custom":{"minecraft:jump":154,"minecraft:time_since_rest":5946,"minecraft:crouch_one_cm":95,"minecraft:sprint_one_cm":13562,"minecraft:play_time":5946,"minecraft:damage_taken":10,"minecraft:time_since_death":5946,"minecraft:walk_one_cm":1918,"minecraft:sneak_time":31,"minecraft:total_world_time":5946,"minecraft:fall_one_cm":5991,"minecraft:fly_one_cm":47582},"minecraft:used":{"minecraft:sand":10},"minecraft:picked_up":{"minecraft:stick":10,"minecraft:sand":10}},"DataVersion":3953}